abspasschek1-0.1.0.dist-info/licenses/LICENSE
mycheckpkg/__init__.py
mycheckpkg/checker.py
abspasschek1-0.1.0.dist-info/METADATA
abspasschek1-0.1.0.dist-info/WHEEL
abspasschek1-0.1.0.dist-info/entry_points.txt
abspasschek1-0.1.0.dist-info/top_level.txt
abspasschek1-0.1.0.dist-info/RECORD
